imas_muscle3/__init__.py
imas_muscle3/_version.py
imas_muscle3/data_sink_source.py
imas_muscle3/utils.py
imas_muscle3/actors/__init__.py
imas_muscle3/actors/accumulator_component.py
imas_muscle3/actors/olc_component.py
imas_muscle3/actors/sink_component.py
imas_muscle3/actors/sink_source_component.py
imas_muscle3/actors/source_component.py
imas_muscle3/actors/visualization_component.py
imas_muscle3/visualization/base_plotter.py
imas_muscle3/visualization/base_state.py
imas_muscle3/visualization/cli.py
imas_muscle3/visualization/resizable_float_panel.py
imas_muscle3/visualization/visualization_actor.py
imas_muscle3/visualization/examples/machine_description/machine_description.py
imas_muscle3/visualization/examples/machine_description/machine_description.ymmsl
imas_muscle3/visualization/examples/pds/pds.py
imas_muscle3/visualization/examples/pds/pds.ymmsl
imas_muscle3/visualization/examples/simple_1d_plot/simple_1d_plot.py
imas_muscle3/visualization/examples/simple_1d_plot/simple_1d_plot.ymmsl
imas_muscle3-1.0.0.dist-info/licenses/LICENSE.txt
imas_muscle3-1.0.0.dist-info/METADATA
imas_muscle3-1.0.0.dist-info/WHEEL
imas_muscle3-1.0.0.dist-info/top_level.txt
imas_muscle3-1.0.0.dist-info/RECORD
