Metadata-Version: 2.4
Name: imas-muscle3
Version: 1.0.0
Summary: IMAS MUSCLE3 tools
Author-email: Mike Sanders <msanders@ignitioncomputing.com>
Project-URL: homepage, https://github.com/iterorganization/IMAS-MUSCLE3
Classifier: Development Status :: 3 - Alpha
Classifier: Environment :: Console
Classifier: Environment :: Plugins
Classifier: Framework :: Flake8
Classifier: Framework :: Pytest
Classifier: Framework :: Sphinx
Classifier: Intended Audience :: Developers
Classifier: Intended Audience :: Science/Research
Classifier: Intended Audience :: System Administrators
Classifier: License :: OSI Approved :: GNU Lesser General Public License v3 (LGPLv3)
Classifier: Natural Language :: English
Classifier: Operating System :: POSIX
Classifier: Operating System :: POSIX :: Linux
Classifier: Programming Language :: Python
Classifier: Programming Language :: Python :: 3
Classifier: Programming Language :: Python :: 3.8
Classifier: Programming Language :: Python :: 3.9
Classifier: Programming Language :: Unix Shell
Classifier: Topic :: Scientific/Engineering
Classifier: Topic :: Scientific/Engineering :: Physics
Classifier: Topic :: Software Development :: Libraries
Classifier: Topic :: Software Development :: Libraries :: Python Modules
Classifier: Topic :: System
Classifier: Topic :: System :: Software Distribution
Classifier: Topic :: Utilities
Requires-Python: >=3.7
License-File: LICENSE.txt
Requires-Dist: numpy>=1.15.4
Requires-Dist: importlib_resources
Requires-Dist: rich
Requires-Dist: packaging
Requires-Dist: imas-python
Requires-Dist: imas-validator
Requires-Dist: muscle3
Requires-Dist: panel
Requires-Dist: holoviews
Requires-Dist: hvplot
Requires-Dist: xarray
Provides-Extra: all
Requires-Dist: imas-muscle3[docs,linting,test]; extra == "all"
Provides-Extra: docs
Requires-Dist: sphinx<7.0.0,>=6.0.0; extra == "docs"
Requires-Dist: sphinx-autosummary-accessors>=0.1.2; extra == "docs"
Requires-Dist: sphinx_immaterial<0.12,>=0.11.0; extra == "docs"
Requires-Dist: recommonmark>=0.6; extra == "docs"
Provides-Extra: test
Requires-Dist: pytest>=5.4.1; extra == "test"
Requires-Dist: pytest-cov>=0.6; extra == "test"
Requires-Dist: pytest-xdist; extra == "test"
Requires-Dist: pytest-randomly; extra == "test"
Provides-Extra: linting
Requires-Dist: black<25,>=24; extra == "linting"
Requires-Dist: flake8; extra == "linting"
Requires-Dist: mypy; extra == "linting"
Requires-Dist: isort; extra == "linting"
Dynamic: license-file
